{
    "niv": {
        "branch": "master",
        "description": "Easy dependency management for Nix projects",
        "homepage": "https://github.com/nmattia/niv",
        "owner": "nmattia",
        "repo": "niv",
        "rev": "1dd094156b249586b66c16200ecfd365c7428dc0",
        "sha256": "1b2vjnn8iac5iiqszjc2v1s1ygh0yri998c0k3s4x4kn0dsqik21",
        "type": "tarball",
        "url": "https://github.com/nmattia/niv/archive/1dd094156b249586b66c16200ecfd365c7428dc0.tar.gz",
        "url_template": "https://github.com/<owner>/<repo>/archive/<rev>.tar.gz"
    },
    "nixpkgs": {
        "branch": "master",
        "description": "Nix Packages collection",
        "homepage": null,
        "owner": "nixos",
        "repo": "nixpkgs",
        "rev": "2e2b068e0435be6fde2ceccf98be3659c88a3f8c",
        "sha256": "0fwrwq541h418y0zqn0mkg3m3ibvnycqm0s6jagxkl0jnrnrfqv9",
        "type": "tarball",
        "url": "https://github.com/nixos/nixpkgs/archive/2e2b068e0435be6fde2ceccf98be3659c88a3f8c.tar.gz",
        "url_template": "https://github.com/<owner>/<repo>/archive/<rev>.tar.gz"
    },
    "ormolu": {
        "branch": "master",
        "description": "A formatter for Haskell source code",
        "homepage": null,
        "owner": "tweag",
        "repo": "ormolu",
        "rev": "397fc55b67fb94cfa1749049d372c2a7891f4720",
        "sha256": "0dlh8b9xr7j4ynk3fwa8f2ixn535mkvsaarnfcnh15jncdmnj0y7",
        "type": "tarball",
        "url": "https://github.com/tweag/ormolu/archive/397fc55b67fb94cfa1749049d372c2a7891f4720.tar.gz",
        "url_template": "https://github.com/<owner>/<repo>/archive/<rev>.tar.gz"
    }
}
